setup.py
django_nearly_solid.egg-info/PKG-INFO
django_nearly_solid.egg-info/SOURCES.txt
django_nearly_solid.egg-info/dependency_links.txt
django_nearly_solid.egg-info/not-zip-safe
django_nearly_solid.egg-info/top_level.txt
examples/__init__.py
examples/simple_shop/__init__.py
examples/simple_shop/manage.py
examples/simple_shop/adapters/__init__.py
examples/simple_shop/adapters/image_storage.py
examples/simple_shop/project/__init__.py
examples/simple_shop/project/asgi.py
examples/simple_shop/project/settings.py
examples/simple_shop/project/urls.py
examples/simple_shop/project/wsgi.py
examples/simple_shop/shop/__init__.py
examples/simple_shop/shop/admin.py
examples/simple_shop/shop/apps.py
examples/simple_shop/shop/container.py
examples/simple_shop/shop/entities.py
examples/simple_shop/shop/enums.py
examples/simple_shop/shop/image_storage.py
examples/simple_shop/shop/models.py
examples/simple_shop/shop/services.py
examples/simple_shop/shop/tests.py
examples/simple_shop/shop/views.py
examples/simple_shop/shop/migrations/__init__.py
ns/__init__.py
ns/errors.py
ns/utils.py
ns/application_layer/__init__.py
ns/application_layer/apps.py
ns/application_layer/decorators.py
ns/application_layer/registry.py
ns/application_layer/typings.py
ns/application_layer/entities/__init__.py
ns/application_layer/entities/application.py
ns/application_layer/entities/entities.py
ns/application_layer/entities/methods.py
ns/application_layer/entities/props.py
ns/application_layer/entities/services.py
ns/application_layer/entities/types.py
ns/application_layer/serialization/__init__.py
ns/application_layer/serialization/application.py
ns/application_layer/serialization/dataclass_entities.py
ns/application_layer/serialization/django_models.py
ns/application_layer/serialization/entities.py
ns/application_layer/serialization/enum_entities.py
ns/application_layer/serialization/methods.py
ns/application_layer/serialization/props.py
ns/application_layer/serialization/pydantic_entities.py
ns/application_layer/serialization/services.py
ns/application_layer/serialization/types.py
ns/auth/__init__.py
ns/auth/contextvars.py
ns/auth/decorators.py
ns/auth/interface.py
ns/auth/middleware.py
ns/auth/provider.py
