Metadata-Version: 2.1
Name: django-nearly-solid
Version: 0.3.1
Summary: UNKNOWN
Home-page: https://github.com/romanukov/django-nearly-solid
Author: Artem Romanukov
License: MIT
Platform: UNKNOWN
Requires: django
Requires: pydantic
